{"web":{"client_id":"70745149420-racaejoapoqb7ale9jp6urbs06d6m4pc.apps.googleusercontent.com","project_id":"imposing-gadget-434020-h0","auth_uri":"https://accounts.google.com/o/oauth2/auth","token_uri":"https://oauth2.googleapis.com/token","auth_provider_x509_cert_url":"https://www.googleapis.com/oauth2/v1/certs","client_secret":"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","redirect_uris":["http://localhost:8888","http://localhost:8888/Callback","http://localhost:8889","http://localhost:8889/Callback","http://localhost:8010","http://localhost:8010/Callback","http://localhost:8050","http://localhost:8050/Callback"]}}